[{"days":1366, "count":1},{"days":30, "count":386},{"days":31, "count":324},{"days":32, "count":517},{"days":33, "count":457},{"days":34, "count":439},{"days":35, "count":447},{"days":36, "count":393},{"days":37, "count":245},{"days":38, "count":208},{"days":39, "count":328},{"days":40, "count":294},{"days":41, "count":303},{"days":42, "count":310},{"days":43, "count":252},{"days":44, "count":163},{"days":45, "count":159},{"days":46, "count":210},{"days":47, "count":270},{"days":48, "count":234},{"days":49, "count":248},{"days":50, "count":227},{"days":51, "count":140},{"days":52, "count":105},{"days":53, "count":177},{"days":54, "count":169},{"days":55, "count":169},{"days":56, "count":188},{"days":57, "count":161},{"days":58, "count":98},{"days":59, "count":107},{"days":60, "count":126},{"days":61, "count":137},{"days":62, "count":151},{"days":63, "count":120},{"days":64, "count":136},{"days":65, "count":100},{"days":66, "count":86},{"days":67, "count":101},{"days":68, "count":121},{"days":69, "count":110},{"days":70, "count":136},{"days":71, "count":107},{"days":72, "count":67},{"days":73, "count":50},{"days":74, "count":120},{"days":75, "count":100},{"days":76, "count":118},{"days":77, "count":92},{"days":78, "count":89},{"days":79, "count":55},{"days":80, "count":61},{"days":81, "count":92},{"days":82, "count":72},{"days":83, "count":75},{"days":84, "count":90},{"days":85, "count":70},{"days":86, "count":53},{"days":87, "count":40},{"days":88, "count":80},{"days":89, "count":88},{"days":90, "count":103},{"days":91, "count":93},{"days":92, "count":77},{"days":93, "count":35},{"days":94, "count":38},{"days":95, "count":72},{"days":96, "count":60},{"days":97, "count":83},{"days":98, "count":83},{"days":99, "count":68},{"days":100, "count":32},{"days":101, "count":40},{"days":102, "count":74},{"days":103, "count":62},{"days":104, "count":74},{"days":105, "count":75},{"days":106, "count":53},{"days":107, "count":36},{"days":108, "count":34},{"days":109, "count":68},{"days":110, "count":60},{"days":111, "count":65},{"days":112, "count":57},{"days":113, "count":79},{"days":114, "count":29},{"days":115, "count":38},{"days":116, "count":49},{"days":117, "count":50},{"days":118, "count":53},{"days":119, "count":53},{"days":120, "count":42},{"days":121, "count":27},{"days":122, "count":23},{"days":123, "count":33},{"days":124, "count":32},{"days":125, "count":41},{"days":126, "count":53},{"days":127, "count":57},{"days":128, "count":26},{"days":129, "count":24},{"days":130, "count":40},{"days":131, "count":45},{"days":132, "count":34},{"days":133, "count":40},{"days":134, "count":32},{"days":135, "count":14},{"days":136, "count":12},{"days":137, "count":33},{"days":138, "count":40},{"days":139, "count":46},{"days":140, "count":42},{"days":141, "count":34},{"days":142, "count":18},{"days":143, "count":14},{"days":144, "count":28},{"days":145, "count":26},{"days":146, "count":24},{"days":147, "count":35},{"days":148, "count":28},{"days":149, "count":17},{"days":150, "count":19},{"days":151, "count":24},{"days":152, "count":39},{"days":153, "count":29},{"days":154, "count":24},{"days":155, "count":22},{"days":156, "count":11},{"days":157, "count":6},{"days":158, "count":21},{"days":159, "count":22},{"days":160, "count":26},{"days":161, "count":33},{"days":162, "count":13},{"days":163, "count":14},{"days":164, "count":18},{"days":165, "count":24},{"days":166, "count":19},{"days":167, "count":24},{"days":168, "count":27},{"days":169, "count":18},{"days":170, "count":12},{"days":171, "count":10},{"days":172, "count":13},{"days":173, "count":12},{"days":174, "count":18},{"days":175, "count":16},{"days":176, "count":16},{"days":177, "count":12},{"days":178, "count":5},{"days":179, "count":18},{"days":180, "count":12},{"days":181, "count":18},{"days":182, "count":19},{"days":183, "count":10},{"days":184, "count":5},{"days":185, "count":9},{"days":186, "count":12},{"days":187, "count":9},{"days":188, "count":16},{"days":189, "count":13},{"days":190, "count":17},{"days":191, "count":8},{"days":192, "count":5},{"days":193, "count":5},{"days":194, "count":13},{"days":195, "count":19},{"days":196, "count":14},{"days":197, "count":11},{"days":198, "count":3},{"days":199, "count":10},{"days":200, "count":18},{"days":201, "count":19},{"days":202, "count":19},{"days":203, "count":16},{"days":204, "count":14},{"days":205, "count":8},{"days":206, "count":8},{"days":207, "count":12},{"days":208, "count":13},{"days":209, "count":6},{"days":210, "count":9},{"days":211, "count":12},{"days":212, "count":5},{"days":213, "count":6},{"days":214, "count":8},{"days":215, "count":12},{"days":216, "count":10},{"days":217, "count":4},{"days":218, "count":7},{"days":219, "count":5},{"days":220, "count":5},{"days":221, "count":6},{"days":222, "count":12},{"days":223, "count":13},{"days":224, "count":6},{"days":225, "count":7},{"days":226, "count":3},{"days":227, "count":4},{"days":228, "count":9},{"days":229, "count":6},{"days":230, "count":6},{"days":231, "count":6},{"days":232, "count":2},{"days":233, "count":4},{"days":234, "count":4},{"days":235, "count":9},{"days":236, "count":12},{"days":237, "count":5},{"days":238, "count":8},{"days":239, "count":8},{"days":240, "count":8},{"days":241, "count":4},{"days":242, "count":2},{"days":243, "count":7},{"days":244, "count":5},{"days":245, "count":10},{"days":246, "count":7},{"days":247, "count":4},{"days":248, "count":1},{"days":249, "count":7},{"days":250, "count":7},{"days":251, "count":6},{"days":252, "count":7},{"days":253, "count":9},{"days":254, "count":4},{"days":255, "count":3},{"days":256, "count":7},{"days":257, "count":6},{"days":258, "count":6},{"days":259, "count":12},{"days":260, "count":9},{"days":261, "count":6},{"days":262, "count":5},{"days":264, "count":4},{"days":265, "count":6},{"days":266, "count":3},{"days":267, "count":2},{"days":268, "count":2},{"days":269, "count":4},{"days":270, "count":4},{"days":271, "count":5},{"days":273, "count":3},{"days":274, "count":6},{"days":275, "count":2},{"days":276, "count":5},{"days":277, "count":1},{"days":278, "count":3},{"days":279, "count":2},{"days":280, "count":3},{"days":281, "count":1},{"days":282, "count":1},{"days":283, "count":1},{"days":284, "count":1},{"days":285, "count":4},{"days":286, "count":2},{"days":287, "count":5},{"days":288, "count":3},{"days":289, "count":3},{"days":290, "count":1},{"days":291, "count":2},{"days":292, "count":4},{"days":293, "count":2},{"days":294, "count":2},{"days":295, "count":3},{"days":296, "count":5},{"days":297, "count":2},{"days":298, "count":3},{"days":299, "count":3},{"days":300, "count":1},{"days":301, "count":3},{"days":302, "count":6},{"days":305, "count":2},{"days":306, "count":3},{"days":308, "count":4},{"days":309, "count":3},{"days":312, "count":1},{"days":313, "count":4},{"days":314, "count":1},{"days":315, "count":4},{"days":316, "count":3},{"days":317, "count":1},{"days":318, "count":3},{"days":319, "count":2},{"days":320, "count":1},{"days":321, "count":2},{"days":322, "count":6},{"days":323, "count":1},{"days":326, "count":3},{"days":327, "count":3},{"days":328, "count":1},{"days":329, "count":3},{"days":330, "count":1},{"days":331, "count":1},{"days":1356, "count":1},{"days":334, "count":2},{"days":335, "count":2},{"days":336, "count":3},{"days":337, "count":1},{"days":338, "count":1},{"days":339, "count":1},{"days":341, "count":1},{"days":342, "count":2},{"days":343, "count":1},{"days":346, "count":1},{"days":348, "count":3},{"days":349, "count":1},{"days":350, "count":1},{"days":355, "count":1},{"days":356, "count":2},{"days":358, "count":2},{"days":360, "count":1},{"days":363, "count":1},{"days":364, "count":2},{"days":365, "count":1},{"days":369, "count":3},{"days":375, "count":1},{"days":380, "count":1},{"days":401, "count":1},{"days":1426, "count":1},{"days":2460, "count":1},{"days":2461, "count":4},{"days":419, "count":1},{"days":446, "count":1},{"days":1103, "count":1},{"days":1510, "count":1},{"days":1512, "count":1},{"days":517, "count":1},{"days":523, "count":1},{"days":524, "count":1},{"days":611, "count":1},{"days":1129, "count":1},{"days":634, "count":2},{"days":635, "count":1},{"days":640, "count":1},{"days":1132, "count":1},{"days":675, "count":2},{"days":691, "count":1},{"days":1720, "count":1},{"days":697, "count":1},{"days":1722, "count":1},{"days":1731, "count":2},{"days":1763, "count":1},{"days":1769, "count":1},{"days":3281, "count":1},{"days":1781, "count":1},{"days":1823, "count":1},{"days":1863, "count":1},{"days":849, "count":1},{"days":1167, "count":1},{"days":2245, "count":1},{"days":1946, "count":1},{"days":924, "count":1},{"days":1055, "count":1},{"days":1365, "count":1}]